{"ok":true,"version":"dash-2025-08-28-atomic-01","updated":"2025-12-15T21:17:43.434Z","count":20000,"latest_time_utc":"2025-12-15T21:00:00.000Z","latest_time_ny":"12/15/2025 16:00:00","latest_close":85773.48,"latest_rsi14":21.36,"latest_composite":-0.5286,"latest_label":"bearish","day_open":89870.98,"day_high":89870.98,"day_low":85740.27,"day_close":85773.48,"day_volume":6349.0512,"prev_close":null,"change_pct":null,"h24_high":89870.98,"h24_low":85740.27,"d7_high":94204.69,"d7_low":85740.27,"d30_high":96558,"d30_low":82104.02,"counts_24h_bullish":0,"counts_24h_neutral":23,"counts_24h_bearish":1,"counts_7d_bullish":1,"counts_7d_neutral":166,"counts_7d_bearish":1,"counts_30d_bullish":4,"counts_30d_neutral":715,"counts_30d_bearish":1}