{"ok":true,"version":"dash-2025-08-28-atomic-01","updated":"2025-10-12T05:31:22.379Z","count":20000,"latest_time_utc":"2025-10-12T05:00:00.000Z","latest_time_ny":"10/12/2025 01:00:00","latest_close":111402.71,"latest_rsi14":44.72,"latest_composite":-0.3195,"latest_label":"neutral","day_open":111424.62,"day_high":112496.69,"day_low":109764.03,"day_close":111402.71,"day_volume":6953.9761,"prev_close":null,"change_pct":null,"h24_high":112496.69,"h24_low":109764.03,"d7_high":126099.22,"d7_low":109764.03,"d30_high":126099.22,"d30_low":108851.99,"counts_24h_bullish":0,"counts_24h_neutral":24,"counts_24h_bearish":0,"counts_7d_bullish":0,"counts_7d_neutral":168,"counts_7d_bearish":0,"counts_30d_bullish":11,"counts_30d_neutral":709,"counts_30d_bearish":0}