{"ok":true,"version":"dash-2025-08-28-atomic-01","updated":"2026-01-05T16:24:10.466Z","count":20000,"latest_time_utc":"2026-01-05T16:00:00.000Z","latest_time_ny":"1/5/2026 11:00:00","latest_close":93870.61,"latest_rsi14":73.14,"latest_composite":0.2272,"latest_label":"neutral","day_open":93045.97,"day_high":93947.6,"day_low":92704.26,"day_close":93870.61,"day_volume":4010.6103,"prev_close":null,"change_pct":null,"h24_high":93947.6,"h24_low":91101.9,"d7_high":93947.6,"d7_low":86984.48,"d30_high":94204.69,"d30_low":84433.02,"counts_24h_bullish":3,"counts_24h_neutral":21,"counts_24h_bearish":0,"counts_7d_bullish":5,"counts_7d_neutral":163,"counts_7d_bearish":0,"counts_30d_bullish":9,"counts_30d_neutral":711,"counts_30d_bearish":0}