{
  "generated_utc": "2026-01-14T17:43:47.482122+00:00",
  "tier": "tier1",
  "price": {
    "source": "coinbase_spot",
    "btc_usd": 97208.375,
    "ts_utc": "2026-01-14T17:43:47.572919+00:00",
    "raw": {
      "data": {
        "amount": "97208.375",
        "base": "BTC",
        "currency": "USD"
      }
    }
  },
  "macro": {
    "dxy": {
      "symbol": "DX-Y.NYB",
      "last": 99.038,
      "prev": 99.134,
      "currency": "USD",
      "exchangeName": "NYB",
      "instrumentType": "INDEX",
      "ts_utc": "2026-01-14T17:43:47.656764+00:00"
    },
    "us10y": {
      "symbol": "%5ETNX",
      "last": 4.142,
      "prev": 4.171,
      "currency": "USD",
      "exchangeName": "CGI",
      "instrumentType": "INDEX",
      "ts_utc": "2026-01-14T17:43:47.733202+00:00",
      "last_yield_pct": 4.142,
      "prev_yield_pct": 4.171
    },
    "es_futures": {
      "symbol": "ES=F",
      "last": 6925.75,
      "prev": 7001.75,
      "currency": "USD",
      "exchangeName": "CME",
      "instrumentType": "FUTURE",
      "ts_utc": "2026-01-14T17:43:47.843296+00:00"
    },
    "nq_futures": {
      "symbol": "NQ=F",
      "last": 25459.75,
      "prev": 25906.0,
      "currency": "USD",
      "exchangeName": "CME",
      "instrumentType": "FUTURE",
      "ts_utc": "2026-01-14T17:43:47.944174+00:00"
    }
  },
  "funding": {
    "source": "okx_swap",
    "symbol": "BTC-USDT-SWAP",
    "fundingRate": -5.0540024256e-05,
    "nextFundingRate": null,
    "ts_exchange_ms": 1768412590292,
    "nextFundingTime_ms": 1768464000000,
    "ts_utc": "2026-01-14T17:43:48.288323+00:00",
    "raw": {
      "code": "0",
      "data": [
        {
          "formulaType": "withRate",
          "fundingRate": "-0.0000505400242560",
          "fundingTime": "1768435200000",
          "impactValue": "20000.0000000000000000",
          "instId": "BTC-USDT-SWAP",
          "instType": "SWAP",
          "interestRate": "0.0001000000000000",
          "maxFundingRate": "0.00375",
          "method": "current_period",
          "minFundingRate": "-0.00375",
          "nextFundingRate": "",
          "nextFundingTime": "1768464000000",
          "premium": "-0.0005361179912348",
          "settFundingRate": "0.0000544822712124",
          "settState": "settled",
          "ts": "1768412590292"
        }
      ],
      "msg": ""
    }
  },
  "etf_flows": {
    "status": "unavailable",
    "reason": "HTTP 403"
  }
}