{"ok":true,"version":"dash-2025-08-28-atomic-01","count":24,"rows":[{"time_utc":"2025-11-13T16:00:00.000Z","time_ny":"11/13/2025 11:00:00","open":101351.99,"high":101512,"low":100499,"close":100589.59,"volume":682.48120143,"trend_score":-0.0112,"momentum_score":-0.3283,"volatility_score":-0.4028,"volume_score":1,"composite_score":0.2202,"composite_label":"neutral","signal_events":null},{"time_utc":"2025-11-13T17:00:00.000Z","time_ny":"11/13/2025 12:00:00","open":100590.82,"high":100773.11,"low":99555,"close":99594.96,"volume":1124.77060956,"trend_score":-0.0157,"momentum_score":-0.4229,"volatility_score":0.1588,"volume_score":1,"composite_score":0.1871,"composite_label":"neutral","signal_events":"RSI<30"},{"time_utc":"2025-11-13T18:00:00.000Z","time_ny":"11/13/2025 13:00:00","open":99598.7,"high":99850,"low":98050,"close":98529.2,"volume":1734.20304581,"trend_score":-0.0204,"momentum_score":-0.5036,"volatility_score":0.8105,"volume_score":1,"composite_score":0.1587,"composite_label":"neutral","signal_events":"RSI<30"},{"time_utc":"2025-11-13T19:00:00.000Z","time_ny":"11/13/2025 14:00:00","open":98529.2,"high":99193.99,"low":98272.88,"close":98629.96,"volume":1057.07176656,"trend_score":-0.0195,"momentum_score":-0.4825,"volatility_score":0.8403,"volume_score":1,"composite_score":0.166,"composite_label":"neutral","signal_events":"RSI<30"},{"time_utc":"2025-11-13T20:00:00.000Z","time_ny":"11/13/2025 15:00:00","open":98632.84,"high":98933.99,"low":97870,"close":98090,"volume":1583.13254737,"trend_score":-0.0217,"momentum_score":-0.5213,"volatility_score":0.8324,"volume_score":1,"composite_score":0.1524,"composite_label":"neutral","signal_events":"RSI<30"},{"time_utc":"2025-11-13T21:00:00.000Z","time_ny":"11/13/2025 16:00:00","open":98085.9,"high":98842.76,"low":97907.72,"close":98738.14,"volume":678.64300743,"trend_score":-0.0181,"momentum_score":-0.3869,"volatility_score":1,"volume_score":0.2479,"composite_score":-0.0524,"composite_label":"neutral","signal_events":null},{"time_utc":"2025-11-13T22:00:00.000Z","time_ny":"11/13/2025 17:00:00","open":98741.98,"high":99887.45,"low":98572.9,"close":99795.65,"volume":682.69522316,"trend_score":-0.0126,"momentum_score":-0.2006,"volatility_score":1,"volume_score":0.1978,"composite_score":-0.0051,"composite_label":"neutral","signal_events":null},{"time_utc":"2025-11-13T23:00:00.000Z","time_ny":"11/13/2025 18:00:00","open":99795.65,"high":100447,"low":99504,"close":99614.54,"volume":608.68676053,"trend_score":-0.0132,"momentum_score":-0.22,"volatility_score":1,"volume_score":0.045,"composite_score":-0.0627,"composite_label":"neutral","signal_events":null},{"time_utc":"2025-11-14T00:00:00.000Z","time_ny":"11/13/2025 19:00:00","open":99610.49,"high":99736.32,"low":98662.73,"close":98929.36,"volume":686.97110574,"trend_score":-0.0162,"momentum_score":-0.2899,"volatility_score":1,"volume_score":0.1397,"composite_score":-0.0555,"composite_label":"neutral","signal_events":null},{"time_utc":"2025-11-14T01:00:00.000Z","time_ny":"11/13/2025 20:00:00","open":98929.7,"high":99520,"low":98658.02,"close":99212.68,"volume":631.70612799,"trend_score":-0.0144,"momentum_score":-0.2404,"volatility_score":1,"volume_score":0.0194,"composite_score":-0.0785,"composite_label":"neutral","signal_events":null},{"time_utc":"2025-11-14T02:00:00.000Z","time_ny":"11/13/2025 21:00:00","open":99212.19,"high":99836.1,"low":99193.69,"close":99574.94,"volume":348.84300774,"trend_score":-0.0123,"momentum_score":-0.1781,"volatility_score":0.9197,"volume_score":-0.4342,"composite_score":-0.2082,"composite_label":"neutral","signal_events":null},{"time_utc":"2025-11-14T03:00:00.000Z","time_ny":"11/13/2025 22:00:00","open":99574.94,"high":99615.3,"low":98760.49,"close":99095.36,"volume":298.38222721,"trend_score":-0.0143,"momentum_score":-0.233,"volatility_score":0.6452,"volume_score":-0.5159,"composite_score":-0.2544,"composite_label":"neutral","signal_events":null},{"time_utc":"2025-11-14T04:00:00.000Z","time_ny":"11/13/2025 23:00:00","open":99095.39,"high":99133.94,"low":96682,"close":97780.08,"volume":989.12005369,"trend_score":-0.0203,"momentum_score":-0.3594,"volatility_score":0.7136,"volume_score":0.5038,"composite_score":0.0414,"composite_label":"neutral","signal_events":null},{"time_utc":"2025-11-14T05:00:00.000Z","time_ny":"11/14/2025 00:00:00","open":97782.45,"high":97999.15,"low":96988.75,"close":97479.32,"volume":624.61176241,"trend_score":-0.0213,"momentum_score":-0.3844,"volatility_score":0.5387,"volume_score":-0.0791,"composite_score":-0.1616,"composite_label":"neutral","signal_events":null},{"time_utc":"2025-11-14T06:00:00.000Z","time_ny":"11/14/2025 01:00:00","open":97479.32,"high":97550,"low":95900.94,"close":97516,"volume":787.22165253,"trend_score":-0.0206,"momentum_score":-0.3773,"volatility_score":0.5024,"volume_score":0.107,"composite_score":-0.097,"composite_label":"neutral","signal_events":null},{"time_utc":"2025-11-14T07:00:00.000Z","time_ny":"11/14/2025 02:00:00","open":97504.64,"high":97695.54,"low":96726.6,"close":97093.95,"volume":444.31860313,"trend_score":-0.0221,"momentum_score":-0.4143,"volatility_score":0.3445,"volume_score":-0.3886,"composite_score":-0.275,"composite_label":"neutral","signal_events":"RSI<30"},{"time_utc":"2025-11-14T08:00:00.000Z","time_ny":"11/14/2025 03:00:00","open":97093.94,"high":97385.32,"low":96720.01,"close":97313.86,"volume":412.22328824,"trend_score":-0.0204,"momentum_score":-0.3687,"volatility_score":0.2559,"volume_score":-0.4424,"composite_score":-0.2772,"composite_label":"neutral","signal_events":null},{"time_utc":"2025-11-14T09:00:00.000Z","time_ny":"11/14/2025 04:00:00","open":97319.09,"high":97487.85,"low":96612.49,"close":96799.58,"volume":296.65252558,"trend_score":-0.0224,"momentum_score":-0.4161,"volatility_score":0.1636,"volume_score":-0.5996,"composite_score":-0.346,"composite_label":"neutral","signal_events":"RSI<30"},{"time_utc":"2025-11-14T10:00:00.000Z","time_ny":"11/14/2025 05:00:00","open":96799.57,"high":97245.11,"low":96601,"close":96700.5,"volume":238.46251426,"trend_score":-0.0222,"momentum_score":-0.4251,"volatility_score":-0.1483,"volume_score":-0.67,"composite_score":-0.3724,"composite_label":"neutral","signal_events":"RSI<30"},{"time_utc":"2025-11-14T11:00:00.000Z","time_ny":"11/14/2025 06:00:00","open":96697.75,"high":96901.08,"low":95666,"close":96124,"volume":554.78946264,"trend_score":-0.0243,"momentum_score":-0.4755,"volatility_score":-0.9435,"volume_score":-0.2329,"composite_score":-0.2442,"composite_label":"neutral","signal_events":"RSI<30"},{"time_utc":"2025-11-14T12:00:00.000Z","time_ny":"11/14/2025 07:00:00","open":96124,"high":96124.48,"low":94480,"close":95282.4,"volume":1439.99720736,"trend_score":-0.0276,"momentum_score":-0.5391,"volatility_score":-0.8566,"volume_score":0.8919,"composite_score":0.1084,"composite_label":"neutral","signal_events":"RSI<30"},{"time_utc":"2025-11-14T13:00:00.000Z","time_ny":"11/14/2025 08:00:00","open":95282.4,"high":95630.13,"low":94455.98,"close":95147.49,"volume":1384.90710816,"trend_score":-0.0274,"momentum_score":-0.5485,"volatility_score":-1,"volume_score":0.789,"composite_score":0.071,"composite_label":"neutral","signal_events":"RSI<30"},{"time_utc":"2025-11-14T14:00:00.000Z","time_ny":"11/14/2025 09:00:00","open":95147.49,"high":96728,"low":94853.36,"close":96464.01,"volume":2051.8482786,"trend_score":-0.0198,"momentum_score":-0.2741,"volatility_score":-0.2129,"volume_score":1,"composite_score":0.2354,"composite_label":"neutral","signal_events":null},{"time_utc":"2025-11-14T15:00:00.000Z","time_ny":"11/14/2025 10:00:00","open":96462.41,"high":96507.88,"low":95778.3,"close":96296.6,"volume":401.09257889,"trend_score":-0.0198,"momentum_score":-0.2913,"volatility_score":-0.2379,"volume_score":-0.4703,"composite_score":-0.2605,"composite_label":"neutral","signal_events":null}]}