{"ok":true,"version":"dash-2025-08-28-atomic-01","count":24,"rows":[{"time_utc":"2025-10-31T22:00:00.000Z","time_ny":"10/31/2025 18:00:00","open":109504.93,"high":109746.76,"low":109418.58,"close":109521.92,"volume":69.06502184,"trend_score":0.0004,"momentum_score":-0.004,"volatility_score":-0.6883,"volume_score":-0.7644,"composite_score":-0.256,"composite_label":"neutral","signal_events":null},{"time_utc":"2025-10-31T23:00:00.000Z","time_ny":"10/31/2025 19:00:00","open":109521.91,"high":109633.99,"low":109457.01,"close":109555.27,"volume":61.75772628,"trend_score":0.0008,"momentum_score":0.0018,"volatility_score":-1,"volume_score":-0.7848,"composite_score":-0.2608,"composite_label":"neutral","signal_events":null},{"time_utc":"2025-11-01T00:00:00.000Z","time_ny":"10/31/2025 20:00:00","open":109555.63,"high":109700.98,"low":109342.47,"close":109678.59,"volume":70.49447207,"trend_score":0.0014,"momentum_score":0.0241,"volatility_score":-1,"volume_score":-0.7442,"composite_score":-0.2396,"composite_label":"neutral","signal_events":null},{"time_utc":"2025-11-01T01:00:00.000Z","time_ny":"10/31/2025 21:00:00","open":109675.44,"high":109992.14,"low":109632.27,"close":109670.4,"volume":76.47163168,"trend_score":0.0014,"momentum_score":0.0225,"volatility_score":-1,"volume_score":-0.7208,"composite_score":-0.2323,"composite_label":"neutral","signal_events":null},{"time_utc":"2025-11-01T02:00:00.000Z","time_ny":"10/31/2025 22:00:00","open":109670.41,"high":109800,"low":109411.02,"close":109717.01,"volume":84.06044287,"trend_score":0.0017,"momentum_score":0.0319,"volatility_score":-1,"volume_score":-0.6923,"composite_score":-0.2196,"composite_label":"neutral","signal_events":null},{"time_utc":"2025-11-01T03:00:00.000Z","time_ny":"10/31/2025 23:00:00","open":109717.02,"high":110240,"low":109712.13,"close":110174.08,"volume":113.50274904,"trend_score":0.0038,"momentum_score":0.1218,"volatility_score":-0.9857,"volume_score":-0.5375,"composite_score":-0.1373,"composite_label":"neutral","signal_events":null},{"time_utc":"2025-11-01T04:00:00.000Z","time_ny":"11/1/2025 00:00:00","open":110174.08,"high":110500,"low":110058.48,"close":110221.61,"volume":90.30531803,"trend_score":0.0041,"momentum_score":0.1308,"volatility_score":-1,"volume_score":-0.6253,"composite_score":-0.1635,"composite_label":"neutral","signal_events":null},{"time_utc":"2025-11-01T05:00:00.000Z","time_ny":"11/1/2025 01:00:00","open":110223.48,"high":110327.96,"low":109966.92,"close":110073.63,"volume":51.52199817,"trend_score":0.0035,"momentum_score":0.0931,"volatility_score":-1,"volume_score":-0.7802,"composite_score":-0.2279,"composite_label":"neutral","signal_events":null},{"time_utc":"2025-11-01T06:00:00.000Z","time_ny":"11/1/2025 02:00:00","open":110073.63,"high":110113.91,"low":109882.08,"close":109942.24,"volume":39.99828729,"trend_score":0.0028,"momentum_score":0.0593,"volatility_score":-0.9015,"volume_score":-0.827,"composite_score":-0.255,"composite_label":"neutral","signal_events":null},{"time_utc":"2025-11-01T07:00:00.000Z","time_ny":"11/1/2025 03:00:00","open":109942.24,"high":110208.94,"low":109927.44,"close":110016.68,"volume":56.24313424,"trend_score":0.0031,"momentum_score":0.0767,"volatility_score":-1,"volume_score":-0.7446,"composite_score":-0.2216,"composite_label":"neutral","signal_events":null},{"time_utc":"2025-11-01T08:00:00.000Z","time_ny":"11/1/2025 04:00:00","open":110016.68,"high":110209.47,"low":110016.68,"close":110186.26,"volume":49.44957418,"trend_score":0.004,"momentum_score":0.1168,"volatility_score":-1,"volume_score":-0.7629,"composite_score":-0.214,"composite_label":"neutral","signal_events":null},{"time_utc":"2025-11-01T09:00:00.000Z","time_ny":"11/1/2025 05:00:00","open":110186.26,"high":110190.93,"low":109896.58,"close":109936.14,"volume":77.52336648,"trend_score":0.003,"momentum_score":0.0448,"volatility_score":-1,"volume_score":-0.5572,"composite_score":-0.1698,"composite_label":"neutral","signal_events":null},{"time_utc":"2025-11-01T10:00:00.000Z","time_ny":"11/1/2025 06:00:00","open":109936.15,"high":110100,"low":109771.54,"close":110089.5,"volume":44.25261385,"trend_score":0.0037,"momentum_score":0.0838,"volatility_score":-1,"volume_score":-0.7109,"composite_score":-0.2078,"composite_label":"neutral","signal_events":null},{"time_utc":"2025-11-01T11:00:00.000Z","time_ny":"11/1/2025 07:00:00","open":110089.6,"high":110166,"low":109932.48,"close":110065.37,"volume":38.22085969,"trend_score":0.0036,"momentum_score":0.0764,"volatility_score":-1,"volume_score":-0.7112,"composite_score":-0.2104,"composite_label":"neutral","signal_events":null},{"time_utc":"2025-11-01T12:00:00.000Z","time_ny":"11/1/2025 08:00:00","open":110065.36,"high":110133,"low":109927.45,"close":109953.01,"volume":45.41734701,"trend_score":0.0031,"momentum_score":0.0405,"volatility_score":-1,"volume_score":-0.5995,"composite_score":-0.1853,"composite_label":"neutral","signal_events":null},{"time_utc":"2025-11-01T13:00:00.000Z","time_ny":"11/1/2025 09:00:00","open":109955.97,"high":109995.28,"low":109608.28,"close":109891.24,"volume":73.794854,"trend_score":0.0028,"momentum_score":0.0203,"volatility_score":-1,"volume_score":-0.2646,"composite_score":-0.0805,"composite_label":"neutral","signal_events":null},{"time_utc":"2025-11-01T14:00:00.000Z","time_ny":"11/1/2025 10:00:00","open":109891.23,"high":109945.17,"low":109667.45,"close":109881.08,"volume":120.50058073,"trend_score":0.0026,"momentum_score":0.0169,"volatility_score":-1,"volume_score":0.3424,"composite_score":0.1206,"composite_label":"neutral","signal_events":null},{"time_utc":"2025-11-01T15:00:00.000Z","time_ny":"11/1/2025 11:00:00","open":109881.08,"high":110297.73,"low":109851.85,"close":110256.93,"volume":121.42882508,"trend_score":0.0041,"momentum_score":0.1346,"volatility_score":-1,"volume_score":0.5844,"composite_score":0.241,"composite_label":"neutral","signal_events":null},{"time_utc":"2025-11-01T16:00:00.000Z","time_ny":"11/1/2025 12:00:00","open":110256.92,"high":110493.52,"low":110143.14,"close":110420.37,"volume":94.65032295,"trend_score":0.0047,"momentum_score":0.1806,"volatility_score":-1,"volume_score":0.2946,"composite_score":0.16,"composite_label":"neutral","signal_events":null},{"time_utc":"2025-11-01T17:00:00.000Z","time_ny":"11/1/2025 13:00:00","open":110417.01,"high":110450,"low":109998.45,"close":110159.29,"volume":130.31082286,"trend_score":0.0032,"momentum_score":0.0817,"volatility_score":-1,"volume_score":0.7271,"composite_score":0.2707,"composite_label":"neutral","signal_events":null},{"time_utc":"2025-11-01T18:00:00.000Z","time_ny":"11/1/2025 14:00:00","open":110159.29,"high":110325.6,"low":110143.51,"close":110286.16,"volume":47.56817725,"trend_score":0.0036,"momentum_score":0.1203,"volatility_score":-0.8593,"volume_score":-0.3604,"composite_score":-0.0788,"composite_label":"neutral","signal_events":null},{"time_utc":"2025-11-01T19:00:00.000Z","time_ny":"11/1/2025 15:00:00","open":110286.16,"high":110292.48,"low":110166.47,"close":110252.53,"volume":51.47156499,"trend_score":0.0032,"momentum_score":0.107,"volatility_score":-0.8238,"volume_score":-0.3031,"composite_score":-0.0643,"composite_label":"neutral","signal_events":null},{"time_utc":"2025-11-01T20:00:00.000Z","time_ny":"11/1/2025 16:00:00","open":110252.53,"high":110471.62,"low":110237.62,"close":110364.99,"volume":49.25047121,"trend_score":0.0034,"momentum_score":0.1436,"volatility_score":-0.77,"volume_score":-0.3235,"composite_score":-0.0588,"composite_label":"neutral","signal_events":null},{"time_utc":"2025-11-01T21:00:00.000Z","time_ny":"11/1/2025 17:00:00","open":110365,"high":110397.41,"low":110310.2,"close":110313.11,"volume":16.49570603,"trend_score":0.0028,"momentum_score":0.1208,"volatility_score":-0.694,"volume_score":-0.7637,"composite_score":-0.2134,"composite_label":"neutral","signal_events":null}]}