{
  "generated_utc": "2026-01-25T11:20:32.092284+00:00",
  "schema": "btc-data-report-v1",
  "status": {
    "ok": true,
    "missing_files": [],
    "errors": {}
  },
  "data": {
    "dashboard": {
      "ok": true,
      "version": "dash-2025-08-31-atomic-03",
      "updated": "2026-01-25T11:20:31.570Z",
      "count": 20000,
      "latest_time_utc": "2026-01-25T11:00:00.000Z",
      "latest_time_ny": "1/25/2026 06:00:00",
      "latest_close": 88479.43,
      "latest_rsi14": 36.68,
      "latest_composite": -0.4171,
      "latest_label": "neutral",
      "day_open": 88518.1,
      "day_high": 88518.1,
      "day_low": 88479.43,
      "day_close": 88479.43,
      "day_volume": 87.0283,
      "prev_close": null,
      "change_pct": null,
      "h24_high": 89390.21,
      "h24_low": 88153.23,
      "d7_high": 95444.4,
      "d7_low": 87501.32,
      "d30_high": 97676.01,
      "d30_low": 86779,
      "counts_24h_bullish": 0,
      "counts_24h_neutral": 24,
      "counts_24h_bearish": 0,
      "counts_7d_bullish": 0,
      "counts_7d_neutral": 168,
      "counts_7d_bearish": 0,
      "counts_30d_bullish": 14,
      "counts_30d_neutral": 706,
      "counts_30d_bearish": 0
    },
    "latest": {
      "ok": true,
      "version": "dash-2025-08-31-atomic-03",
      "count": 1,
      "rows": [
        {
          "time_utc": "2026-01-25T11:00:00.000Z",
          "time_ny": "1/25/2026 06:00:00",
          "open": 88518.1,
          "high": 88518.11,
          "low": 88442.14,
          "close": 88479.43,
          "volume": 13.45834039,
          "trend_score": -0.0046,
          "momentum_score": -0.2813,
          "volatility_score": 1,
          "volume_score": -0.9653,
          "composite_score": -0.4171,
          "composite_label": "neutral",
          "signal_events": null
        }
      ]
    },
    "last-24h": {
      "ok": true,
      "version": "dash-2025-08-31-atomic-03",
      "summary": {
        "bars": 24,
        "open_first": 89450.0,
        "close_last": 88479.43,
        "high": 89450.01,
        "low": 88000.0,
        "change_pct": -1.0850419228619401,
        "volume_sum": 1935.39796228,
        "first_time_utc": "2026-01-24T12:00:00.000Z",
        "last_time_utc": "2026-01-25T11:00:00.000Z"
      },
      "rows_tail": [
        {
          "time_utc": "2026-01-25T09:00:00.000Z",
          "time_ny": "1/25/2026 04:00:00",
          "open": 88153.23,
          "high": 88359.55,
          "low": 88097.98,
          "close": 88266.18,
          "volume": 63.42046646,
          "trend_score": -0.0057,
          "momentum_score": -0.4412,
          "volatility_score": 1,
          "volume_score": -0.2721,
          "composite_score": -0.2396,
          "composite_label": "neutral",
          "signal_events": "RSI<30"
        },
        {
          "time_utc": "2026-01-25T10:00:00.000Z",
          "time_ny": "1/25/2026 05:00:00",
          "open": 88266.17,
          "high": 88540.94,
          "low": 88266.17,
          "close": 88518.1,
          "volume": 73.56999814,
          "trend_score": -0.0042,
          "momentum_score": -0.2504,
          "volatility_score": 1,
          "volume_score": -0.1343,
          "composite_score": -0.1296,
          "composite_label": "neutral",
          "signal_events": null
        },
        {
          "time_utc": "2026-01-25T11:00:00.000Z",
          "time_ny": "1/25/2026 06:00:00",
          "open": 88518.1,
          "high": 88518.11,
          "low": 88442.14,
          "close": 88479.43,
          "volume": 13.45834039,
          "trend_score": -0.0046,
          "momentum_score": -0.2813,
          "volatility_score": 1,
          "volume_score": -0.9653,
          "composite_score": -0.4171,
          "composite_label": "neutral",
          "signal_events": null
        }
      ]
    },
    "90d": {
      "ok": true,
      "version": "dash-2025-08-31-atomic-03",
      "summary": {
        "count": 2160,
        "latest_time_utc": "2026-01-25T11:00:00.000Z",
        "close_last": 88442.14
      }
    },
    "ytd": {
      "ok": true,
      "version": "dash-2025-08-31-atomic-03",
      "summary": {
        "count": 9338,
        "latest_time_utc": "2026-01-25T11:00:00.000Z",
        "close_last": 88479.43
      }
    },
    "2023": {
      "ok": true,
      "version": null,
      "summary": {
        "count": 8753,
        "latest_time_utc": "2023-12-31T23:00:00.000Z",
        "close_last": 42389.77
      }
    },
    "2024": {
      "ok": true,
      "version": null,
      "summary": {
        "count": 8781,
        "latest_time_utc": "2024-12-31T23:00:00.000Z",
        "close_last": 93358.58
      }
    },
    "tier1": {
      "generated_utc": "2026-01-25T11:19:47.962171+00:00",
      "tier": "tier1",
      "price": {
        "source": "coinbase_spot",
        "btc_usd": 88487.395,
        "ts_utc": "2026-01-25T11:19:48.045463+00:00"
      },
      "macro": {
        "dxy": {
          "symbol": "DX-Y.NYB",
          "last": 97.456,
          "prev": 97.599,
          "currency": "USD",
          "exchangeName": "NYB",
          "instrumentType": "INDEX",
          "ts_utc": "2026-01-25T11:19:48.148615+00:00"
        },
        "us10y": {
          "symbol": "%5ETNX",
          "last": 4.239,
          "prev": 4.249,
          "currency": "USD",
          "exchangeName": "CGI",
          "instrumentType": "INDEX",
          "ts_utc": "2026-01-25T11:19:48.228277+00:00",
          "last_yield_pct": 4.239,
          "prev_yield_pct": 4.249
        },
        "es_futures": {
          "symbol": "ES=F",
          "last": 6945.75,
          "prev": 6945.0,
          "currency": "USD",
          "exchangeName": "CME",
          "instrumentType": "FUTURE",
          "ts_utc": "2026-01-25T11:19:48.300810+00:00"
        },
        "nq_futures": {
          "symbol": "NQ=F",
          "last": 25738.25,
          "prev": 25658.25,
          "currency": "USD",
          "exchangeName": "CME",
          "instrumentType": "FUTURE",
          "ts_utc": "2026-01-25T11:19:48.369109+00:00"
        }
      },
      "funding": {
        "source": "okx_swap",
        "symbol": "BTC-USDT-SWAP",
        "fundingRate": 3.25291337446e-05,
        "nextFundingRate": null,
        "ts_exchange_ms": 1769339947233,
        "nextFundingTime_ms": 1769385600000,
        "ts_utc": "2026-01-25T11:19:48.717406+00:00"
      },
      "etf_flows": {
        "status": "unavailable",
        "reason": "HTTP 403"
      },
      "note": "Tier-1: runtime BTC spot + macro + funding snapshot from external APIs.",
      "basis_vs_latest": {
        "latest_close": 88479.43,
        "spot_btc_usd": 88487.395,
        "basis_abs": 7.9650000000110595,
        "basis_pct": 0.00900209235074306
      }
    }
  }
}